[
  {
    "id": "dc22401",
    "url": "https://www.tesla.com/de_DE/findus/location/charger/dc22401",
    "name": "Sunborn Gibraltar",
    "street": "Ocean Village, 35 Marina Bay Square",
    "extended": "",
    "locality": "GX11 1AA Gibraltar",
    "tel": " +350 2 001 6100"
  },
  {
    "id": "dc22199",
    "url": "https://www.tesla.com/de_DE/findus/location/charger/dc22199",
    "name": "The Rock Hotel Gibraltar",
    "street": "3 Europa Road",
    "extended": "",
    "locality": " Gibraltar",
    "tel": " +350 2 007 3000"
  }
]